proteinclustertools/__init__.py
proteinclustertools/pipeline.py
proteinclustertools/layout/__init__.py
proteinclustertools/layout/circle_collision.py
proteinclustertools/layout/circle_layout_tools.py
proteinclustertools/layout/draw_circles.py
proteinclustertools/tools/__init__.py
proteinclustertools/tools/cluster_merging.py
proteinclustertools/tools/cluster_stream.py
proteinclustertools/tools/esm_extract.py
proteinclustertools/tools/esm_wrapper.py
proteinclustertools/tools/hierarchical_clustering.py
proteinclustertools/tools/hmm_cluster_rep.py
proteinclustertools/tools/kmeans.py
proteinclustertools/tools/mmseqs_wrapper.py
proteinclustertools/tools/sanitize_fasta_headers.py
proteinclustertools/tools/summarize_distribution.py
proteinclustertools/tools/vector_cluster_rep.py
proteinclustertools/visuals/__init__.py
proteinclustertools/visuals/annotate.py
proteinclustertools/visuals/circle_plot.py
proteinclustertools/visuals/tree_utils.py
proteinclustertools-1.0.16.dist-info/METADATA
proteinclustertools-1.0.16.dist-info/WHEEL
proteinclustertools-1.0.16.dist-info/RECORD
